CHANGELOG.md
indexserverclient/__init__.py
indexserverclient/api/__init__.py
indexserverclient/api/b_utility/__init__.py
indexserverclient/api/b_utility/b_utility_upload.py
indexserverclient/api/client_notification/__init__.py
indexserverclient/api/client_notification/client_notification_admin_mode.py
indexserverclient/api/client_notification/client_notification_update_task.py
indexserverclient/api/document_events/__init__.py
indexserverclient/api/document_events/document_events_begin_download.py
indexserverclient/api/document_events/document_events_begin_upload.py
indexserverclient/api/document_processor/__init__.py
indexserverclient/api/document_processor/document_processor_process.py
indexserverclient/api/feed_notification/__init__.py
indexserverclient/api/feed_notification/feed_notification_update_action.py
indexserverclient/api/feed_service/__init__.py
indexserverclient/api/feed_service/feed_service_checkin_action.py
indexserverclient/api/feed_service/feed_service_checkout_action.py
indexserverclient/api/feed_service/feed_service_checkout_hash_tag.py
indexserverclient/api/feed_service/feed_service_create_action.py
indexserverclient/api/feed_service/feed_service_create_hash_tag_subscription.py
indexserverclient/api/feed_service/feed_service_find_first_actions.py
indexserverclient/api/feed_service/feed_service_find_first_hash_tag_relation.py
indexserverclient/api/feed_service/feed_service_find_first_notification.py
indexserverclient/api/feed_service/feed_service_find_hash_tag_by_actions.py
indexserverclient/api/feed_service/feed_service_find_hash_tags.py
indexserverclient/api/feed_service/feed_service_find_next_actions.py
indexserverclient/api/feed_service/feed_service_find_next_hash_tag_relation.py
indexserverclient/api/feed_service/feed_service_find_next_notification.py
indexserverclient/api/feed_service/feed_service_find_post_actions.py
indexserverclient/api/feed_service/feed_service_internal_insert_system_action.py
elo_indexserver_client-20.0.0.111.dist-info/METADATA
elo_indexserver_client-20.0.0.111.dist-info/WHEEL
elo_indexserver_client-20.0.0.111.dist-info/RECORD
